myjd_api/__init__.py
myjd_api/run.py
myjd_api/providers/__init__.py
myjd_api/providers/common.py
myjd_api/providers/config.py
myjd_api/providers/files.py
myjd_api/providers/myjd.py
myjd_api/providers/myjdapi.py
myjd_api/providers/requests.py
myjd_api/providers/version.py
myjd_api-1.2.6.dist-info/LICENSE.md
myjd_api-1.2.6.dist-info/METADATA
myjd_api-1.2.6.dist-info/WHEEL
myjd_api-1.2.6.dist-info/entry_points.txt
myjd_api-1.2.6.dist-info/top_level.txt
myjd_api-1.2.6.dist-info/RECORD
