Metadata-Version: 2.1
Name: myjd-api
Version: 1.2.6
Summary: A simple json interface for the MyJDownloader API to be used with Organizr
Home-page: https://github.com/rix1337/MyJD-API
Author: rix1337
Author-email: 
License: UNKNOWN
Platform: UNKNOWN
Classifier: Programming Language :: Python :: 3
Classifier: License :: OSI Approved :: MIT License
Classifier: Operating System :: OS Independent
License-File: LICENSE.md
Requires-Dist: bottle (==0.12.25)
Requires-Dist: pycryptodomex (==3.20.0)
